cobry/__init__.py
cobry/args.py
cobry/command.py
cobry/flag.py
cobry/flag_set.py
cobry-0.1.1.dist-info/LICENSE
cobry-0.1.1.dist-info/METADATA
cobry-0.1.1.dist-info/WHEEL
cobry-0.1.1.dist-info/top_level.txt
cobry-0.1.1.dist-info/RECORD
