Metadata-Version: 2.1
Name: cobry
Version: 0.1.1
Summary: Yet another command line interface toolkit to built versatile and modern CLI applications.
Home-page: https://github.com/tuunit/cobry
Author: Jan Larwig
Author-email: jan@larwig.com
License: BSD 3-Clause License
Platform: UNKNOWN
Classifier: Development Status :: 1 - Planning
Classifier: Intended Audience :: Developers
Classifier: License :: OSI Approved :: BSD License
Classifier: Programming Language :: Python :: 3
Classifier: Operating System :: OS Independent
Requires-Python: >=3.0
